modern_pg/__init__.py
modern_pg/connections.py
modern_pg/decorators.py
modern_pg/helpers.py
modern_pg/py.typed
modern_pg/settings.py
modern_pg/transaction.py
modern_pg-0.1.1.dist-info/WHEEL
modern_pg-0.1.1.dist-info/METADATA
modern_pg-0.1.1.dist-info/RECORD
