Metadata-Version: 2.4
Name: modern-pg
Version: 0.1.1
Summary: PostgreSQL Tools
Keywords: python,postgresql,sqlalchemy
Author: Artur Shiriev
Author-email: Artur Shiriev <me@shiriev.ru>
License-Expression: MIT
Classifier: Programming Language :: Python :: 3.10
Classifier: Programming Language :: Python :: 3.11
Classifier: Programming Language :: Python :: 3.12
Classifier: Programming Language :: Python :: 3.13
Classifier: Typing :: Typed
Classifier: Topic :: Software Development :: Libraries
Requires-Dist: tenacity
Requires-Dist: sqlalchemy[asyncio]
Requires-Dist: asyncpg
Requires-Python: >=3.10, <4
Project-URL: repository, https://github.com/modern-python/sa-utils
